opendp/__init__.py
opendp/smartnoise/__init__.py
opendp/smartnoise/report.py
opendp/smartnoise/_ast/__init__.py
opendp/smartnoise/_ast/ast.py
opendp/smartnoise/_ast/expression.py
opendp/smartnoise/_ast/tokens.py
opendp/smartnoise/_ast/validate.py
opendp/smartnoise/_ast/expressions/__init__.py
opendp/smartnoise/_ast/expressions/date.py
opendp/smartnoise/_ast/expressions/logical.py
opendp/smartnoise/_ast/expressions/numeric.py
opendp/smartnoise/_ast/expressions/sql.py
opendp/smartnoise/_ast/expressions/string.py
opendp/smartnoise/client/__init__.py
opendp/smartnoise/client/restclient/__init__.py
opendp/smartnoise/client/restclient/rest_client.py
opendp/smartnoise/client/restclient/version.py
opendp/smartnoise/client/restclient/models/__init__.py
opendp/smartnoise/client/restclient/models/dataset_document.py
opendp/smartnoise/client/restclient/models/dataset_read_release_request.py
opendp/smartnoise/client/restclient/models/dataset_read_request.py
opendp/smartnoise/client/restclient/models/dataverse_details.py
opendp/smartnoise/client/restclient/models/executerun_ok_response.py
opendp/smartnoise/client/restclient/models/local_csv_details.py
opendp/smartnoise/client/restclient/models/project_run_details.py
opendp/smartnoise/client/restclient/models/register_ok_response.py
opendp/smartnoise/client/restclient/models/release_dataset_document.py
opendp/smartnoise/client/restclient/models/secret.py
opendp/smartnoise/client/restclient/models/secret_put_success.py
opendp/smartnoise/data/__init__.py
opendp/smartnoise/data/adapters.py
opendp/smartnoise/data/dataset_adapter.py
opendp/smartnoise/data/dataverse_adapter.py
opendp/smartnoise/data/local_csv_adapter.py
opendp/smartnoise/evaluation/__init__.py
opendp/smartnoise/evaluation/_aggregation.py
opendp/smartnoise/evaluation/_dp_verification.py
opendp/smartnoise/evaluation/_exploration.py
opendp/smartnoise/evaluation/benchmarking/__init__.py
opendp/smartnoise/evaluation/benchmarking/_base.py
opendp_smartnoise-0.1.4.2.dist-info/METADATA
opendp_smartnoise-0.1.4.2.dist-info/WHEEL
opendp_smartnoise-0.1.4.2.dist-info/top_level.txt
opendp_smartnoise-0.1.4.2.dist-info/RECORD
