Metadata-Version: 2.1
Name: opendp-smartnoise
Version: 0.1.4.2
Summary: UNKNOWN
Home-page: UNKNOWN
Author: opendp-smartnoise
License: UNKNOWN
Platform: UNKNOWN
Requires-Dist: numpy
Requires-Dist: pandas
Requires-Dist: msrest
Requires-Dist: scipy
Requires-Dist: antlr4-python3-runtime (==4.8)
Requires-Dist: pandasql
Requires-Dist: statsmodels
Requires-Dist: pyyaml
Requires-Dist: opendp-smartnoise-core
